liga/pytorch/__init__.py
liga/pytorch/codegen.py
liga/pytorch/pandas.py
liga/pytorch/transforms.py
liga_pytorch-0.3.0.dist-info/METADATA
liga_pytorch-0.3.0.dist-info/WHEEL
liga_pytorch-0.3.0.dist-info/namespace_packages.txt
liga_pytorch-0.3.0.dist-info/top_level.txt
liga_pytorch-0.3.0.dist-info/RECORD
